.travis.yml
LICENSE
README.rst
setup.py
aio_doh.egg-info/PKG-INFO
aio_doh.egg-info/SOURCES.txt
aio_doh.egg-info/dependency_links.txt
aio_doh.egg-info/requires.txt
aio_doh.egg-info/top_level.txt
doh/__init__.py
doh/client.py
doh/exceptions.py
doh/utils.py
tests/test_client.py