Metadata-Version: 1.2
Name: aio-doh
Version: 0.0.4
Summary: Asynchronous DNS-over-HTTPS client for Python
Home-page: https://github.com/ZhukovAlexander/aio-doh
Author: Alexander Zhuko
Author-email: zhukovaa90@gmail.com
License: UNKNOWN
Keywords: python dns https asyncio
Platform: UNKNOWN
Classifier: Development Status :: 3 - Alpha
Classifier: Intended Audience :: Developers
Classifier: License :: OSI Approved :: Apache Software License
Classifier: Operating System :: OS Independent
Classifier: Programming Language :: Python :: 3
Classifier: Topic :: Software Development :: Libraries :: Python Modules
Requires-Python: >=3.6
